ogma/__init__.py
ogma/__main__.py
ogma/codegen.py
ogma/commands/__init__.py
ogma/commands/common.py
ogma/commands/enumtables.py
ogma/commands/enumusage.py
ogma/commands/generate.py
ogma/main.py
ogma/modelutils/__init__.py
ogma/modelutils/sqlalchemywrappers.py
ogma/modelutils/stored_procedures.py
ogma/modelutils/validation.py
ogma/modelutils/value_holder.py
ogma/templates/__init__.py
ogma/templates/generated_annotation.mustache
ogma/templates/generated_header.mustache
ogma/templates/java_enum.mustache
ogma/templates/java_enum_converter.mustache
ogma/templates/jooq_generator_config.mustache
ogma/utils/__init__.py
ogma/version.py
ogma-0.1.0.dist-info/entry_points.txt
ogma-0.1.0.dist-info/LICENSE
ogma-0.1.0.dist-info/WHEEL
ogma-0.1.0.dist-info/METADATA
ogma-0.1.0.dist-info/RECORD
