Metadata-Version: 2.1
Name: ogma
Version: 0.1.0
Summary: Ogma: A database access code generator for Java
Home-page: https://www.github.com/jdevera/ogma
License: MIT
Author: Jacobo de Vera
Author-email: devel@jacobodevera.com
Requires-Python: >=3.6,<4.0
Classifier: Intended Audience :: Developers
Classifier: License :: OSI Approved :: MIT License
Classifier: Programming Language :: Java
Classifier: Programming Language :: Python :: 3
Classifier: Programming Language :: Python :: 3.6
Classifier: Programming Language :: Python :: 3.7
Classifier: Programming Language :: SQL
Classifier: Topic :: Database
Classifier: Topic :: Software Development :: Build Tools
Classifier: Topic :: Software Development :: Code Generators
Classifier: Topic :: Utilities
Requires-Dist: PyMySQL (>=0.9,<0.10)
Requires-Dist: SQLAlchemy (>=1.3,<1.4)
Requires-Dist: argcomplete (>=1.10,<1.11)
Requires-Dist: colorama (>=0.4,<0.5)
Requires-Dist: colored (>=1.3,<1.4)
Requires-Dist: pystache (>=0.5,<0.6)
